segwo/__init__.py
segwo/cov.py
segwo/response.py
segwo/sensitivity.py
segwo/sym.py
segwo-1.2.0.dist-info/METADATA
segwo-1.2.0.dist-info/WHEEL
segwo-1.2.0.dist-info/licenses/LICENSE
segwo-1.2.0.dist-info/RECORD
