Metadata-Version: 2.4
Name: segwo
Version: 1.2.0
Summary: Sensitivity Estimation for Gravitational-Wave Observatories
License: BSD 3-Clause
License-File: LICENSE
Keywords: gravitational-wave,sensitivity curve,noise budget
Author: Jean-Baptiste Bayle
Author-email: j2b.bayle@gmail.com
Requires-Python: >=3.11
Classifier: Intended Audience :: Science/Research
Classifier: Topic :: Scientific/Engineering :: Astronomy
Classifier: Topic :: Scientific/Engineering :: Physics
Requires-Dist: healpy (>=1.18.1,<2.0.0)
Requires-Dist: lisaconstants (>=2.0.1,<3.0.0) ; python_version < "4.0"
Requires-Dist: matplotlib (>=3.10.1,<4.0.0)
Requires-Dist: numpy (>=2.2.4,<3.0.0)
Requires-Dist: pytdi (>=1.3.1,<3.0.0)
Requires-Dist: scipy (>=1.15.2,<2.0.0)
Requires-Dist: sympy (>=1.13.3,<2.0.0)
Project-URL: Documentation, https://j2b.bayle.gitlab.io/segwo
Project-URL: Download, https://gitlab.com/j2b.bayle/segwo/-/releases
Project-URL: Issue Tracker, https://gitlab.com/j2b.bayle/segwo/-/issues
Project-URL: Repository, https://gitlab.com/j2b.bayle/segwo
